AUTHORS.txt
CHANGES.txt
LICENSE.txt
MANIFEST.in
README.txt
setup.py
tipfy/__init__.py
tipfy.ext.jinja2.egg-info/PKG-INFO
tipfy.ext.jinja2.egg-info/SOURCES.txt
tipfy.ext.jinja2.egg-info/dependency_links.txt
tipfy.ext.jinja2.egg-info/entry_points.txt
tipfy.ext.jinja2.egg-info/namespace_packages.txt
tipfy.ext.jinja2.egg-info/not-zip-safe
tipfy.ext.jinja2.egg-info/requires.txt
tipfy.ext.jinja2.egg-info/top_level.txt
tipfy/ext/__init__.py
tipfy/ext/jinja2/__init__.py
tipfy/ext/jinja2/scripts.py